{"cameraMode":{"drawMode":0,"name":"Shaded","section":"Shading Mode"},"sceneLighting":true,"audioPlay":false,"sceneViewState":{"showFog":true,"showMaterialUpdate":false,"showSkybox":true,"showFlares":true,"showImageEffects":true,"showParticleSystems":true},"in2DMode":false,"pivot":{"x":-0.29834938049316409,"y":-0.8175067901611328,"z":-1.7374210357666016},"rotation":{"x":-0.0769646167755127,"y":0.9180507063865662,"z":-0.22058917582035066,"w":-0.3203122019767761},"size":41.86559295654297,"orthographic":false}